LICENSE.txt
MANIFEST.in
README.md
setup.py
assembla/__init__.py
assembla/api.py
assembla/lib.py
assembla/settings.py
assembla.egg-info/PKG-INFO
assembla.egg-info/SOURCES.txt
assembla.egg-info/dependency_links.txt
assembla.egg-info/requires.txt
assembla.egg-info/top_level.txt
assembla/tests/__init__.py
assembla/tests/auth.py
assembla/tests/auth.tmpl.py
assembla/tests/build_test_space.py
assembla/tests/retrieval_tests.py
assembla/tests/write_tests.py