Metadata-Version: 1.1
Name: assembla
Version: 2.4.0
Summary: Python wrapper for the Assembla API
Home-page: http://github.com/markfinger/assembla/
Author: Mark Finger
Author-email: markfinger@gmail.com
License: MIT
Keywords: Assembla API
Platform: any
Classifier: Development Status :: 5 - Production/Stable
Classifier: Intended Audience :: Developers
Classifier: Topic :: Software Development
Classifier: Operating System :: OS Independent
Classifier: Programming Language :: Python
Classifier: License :: OSI Approved :: MIT License
